{
  "ticker": "PLTR",
  "last_updated": "2026-03-15T08:58:29.646731",
  "quarters": [
    {
      "gaap_eps": 0.18498189655071826,
      "adjusted_eps": 0.18498189655071826,
      "gaap_net_income": 475599000.0,
      "adjusted_net_income": 475599000.0,
      "diluted_shares_used": 2571057000.0,
      "adjustments": [],
      "net_adjustment_total": 0.0,
      "filing_date": "2025-09-30",
      "form": "10-Q",
      "ai_analysis": {
        "health": "Good",
        "comment": "調整項目はありません。GAAP EPSがそのまま実質EPSと見なせます。",
        "sources": []
      }
    },
    {
      "gaap_eps": 0.1274827227778402,
      "adjusted_eps": 0.1274827227778402,
      "gaap_net_income": 326727000.0,
      "adjusted_net_income": 326727000.0,
      "diluted_shares_used": 2562912000.0,
      "adjustments": [],
      "net_adjustment_total": 0.0,
      "filing_date": "2025-06-30",
      "form": "10-Q",
      "ai_analysis": {
        "health": "Good",
        "comment": "調整項目はありません。GAAP EPSがそのまま実質EPSと見なせます。",
        "sources": []
      }
    },
    {
      "gaap_eps": 0.08384107288494519,
      "adjusted_eps": 0.131912580528655,
      "gaap_net_income": 214031000.0,
      "adjusted_net_income": 336748810.0,
      "diluted_shares_used": 2552818000.0,
      "adjustments": [
        {
          "item_name": "株式報酬費用",
          "amount": 155339000,
          "unit": "USD",
          "direction": "add_back",
          "pre_tax": true,
          "reason": "非現金費用（ConfigでON/OFF可）",
          "extracted_from": "us-gaap:ShareBasedCompensation",
          "category": "株式報酬 (SBC)",
          "net_amount": 122717810.0,
          "tax_rate_applied": 0.21
        }
      ],
      "net_adjustment_total": 122717810.0,
      "filing_date": "2025-03-31",
      "form": "10-Q",
      "ai_analysis": {
        "health": "Caution",
        "comment": "株式報酬費用155M USDをadd_backした結果、GAAP EPS 0.084からAdjusted EPS 0.132へ約57%増加。SBCは非現金だが株主希薄化の実質コストであり、調整依存度が高いため非GAAP指標の健全性に注意が必要。",
        "sources": [
          {
            "item": "株式報酬費用",
            "snippet": "amount: 155339000, direction: add_back, reason: 非現金費用（ConfigでON/OFF可）, category: 株式報酬 (SBC)"
          }
        ]
      }
    },
    {
      "gaap_eps": 0.02917662259832842,
      "adjusted_eps": 0.02917662259832842,
      "gaap_net_income": 143525000.0,
      "adjusted_net_income": 143525000.0,
      "diluted_shares_used": 4919178000.0,
      "adjustments": [],
      "net_adjustment_total": 0.0,
      "filing_date": "2024-09-30",
      "form": "10-Q",
      "ai_analysis": {
        "health": "Good",
        "comment": "調整項目はありません。GAAP EPSがそのまま実質EPSと見なせます。",
        "sources": []
      }
    },
    {
      "gaap_eps": 0.027772854222643348,
      "adjusted_eps": 0.027772854222643348,
      "gaap_net_income": 134126000.0,
      "adjusted_net_income": 134126000.0,
      "diluted_shares_used": 4829392000.0,
      "adjustments": [],
      "net_adjustment_total": 0.0,
      "filing_date": "2024-06-30",
      "form": "10-Q",
      "ai_analysis": {
        "health": "Good",
        "comment": "調整項目はありません。GAAP EPSがそのまま実質EPSと見なせます。",
        "sources": []
      }
    },
    {
      "gaap_eps": 0.021984436527204828,
      "adjusted_eps": 0.04266357499894796,
      "gaap_net_income": 105530000.0,
      "adjusted_net_income": 204794290.0,
      "diluted_shares_used": 4800214000.0,
      "adjustments": [
        {
          "item_name": "株式報酬費用",
          "amount": 125651000,
          "unit": "USD",
          "direction": "add_back",
          "pre_tax": true,
          "reason": "非現金費用（ConfigでON/OFF可）",
          "extracted_from": "us-gaap:ShareBasedCompensation",
          "category": "株式報酬 (SBC)",
          "net_amount": 99264290.0,
          "tax_rate_applied": 0.21
        }
      ],
      "net_adjustment_total": 99264290.0,
      "filing_date": "2024-03-31",
      "form": "10-Q",
      "ai_analysis": {
        "health": "Caution",
        "comment": "調整項目は株式報酬費用の追加バック1項目のみで、税効果を適切に適用した標準的な非現金調整です。ただし調整額がGAAP EPSをほぼ倍増させる規模であり、PLTR特有の高いSBC依存を考慮すると調整後EPSの質には注意が必要です。透明性は確保されているものの過度な信頼は避けるべきです。",
        "sources": [
          {
            "item": "株式報酬費用",
            "snippet": "amount: 125651000, direction: add_back, reason: 非現金費用（ConfigでON/OFF可）, net_amount: 99264290.0"
          },
          {
            "item": "EPS差異",
            "snippet": "GAAP EPS: 0.021984436527204828, Adjusted EPS: 0.04266357499894796"
          }
        ]
      }
    },
    {
      "gaap_eps": 0.0153734520123839,
      "adjusted_eps": 0.0153734520123839,
      "gaap_net_income": 71505000.0,
      "adjusted_net_income": 71505000.0,
      "diluted_shares_used": 4651200000.0,
      "adjustments": [],
      "net_adjustment_total": 0.0,
      "filing_date": "2023-09-30",
      "form": "10-Q",
      "ai_analysis": {
        "health": "Good",
        "comment": "調整項目はありません。GAAP EPSがそのまま実質EPSと見なせます。",
        "sources": []
      }
    },
    {
      "gaap_eps": 0.00617319717051737,
      "adjusted_eps": 0.00617319717051737,
      "gaap_net_income": 28127000.0,
      "adjusted_net_income": 28127000.0,
      "diluted_shares_used": 4556310000.0,
      "adjustments": [],
      "net_adjustment_total": 0.0,
      "filing_date": "2023-06-30",
      "form": "10-Q",
      "ai_analysis": {
        "health": "Good",
        "comment": "調整項目はありません。GAAP EPSがそのまま実質EPSと見なせます。",
        "sources": []
      }
    },
    {
      "gaap_eps": 0.003788604782363799,
      "adjusted_eps": 0.02422300230130344,
      "gaap_net_income": 16802000.0,
      "adjusted_net_income": 107426060.0,
      "diluted_shares_used": 4434878000.0,
      "adjustments": [
        {
          "item_name": "株式報酬費用",
          "amount": 114714000,
          "unit": "USD",
          "direction": "add_back",
          "pre_tax": true,
          "reason": "非現金費用（ConfigでON/OFF可）",
          "extracted_from": "us-gaap:ShareBasedCompensation",
          "category": "株式報酬 (SBC)",
          "net_amount": 90624060.0,
          "tax_rate_applied": 0.21
        }
      ],
      "net_adjustment_total": 90624060.0,
      "filing_date": "2023-03-31",
      "form": "10-Q",
      "ai_analysis": {
        "health": "Caution",
        "comment": "調整項目は株式報酬費用の加算戻しのみで、非現金費用として一般的な処理ですが、GAAP EPS(0.0038)がAdjusted EPS(0.0242)へ約6倍に跳ね上がる大きな影響を与えています。SBCの高水準は株式希薄化の観点から実質的なコストと見なされる場合があり、調整後の健全性に注意が必要です。",
        "sources": [
          {
            "item": "株式報酬費用",
            "snippet": "非現金費用（ConfigでON/OFF可）"
          }
        ]
      }
    },
    {
      "gaap_eps": -0.029874376888627357,
      "adjusted_eps": -0.029874376888627357,
      "gaap_net_income": -123875000.0,
      "adjusted_net_income": -123875000.0,
      "diluted_shares_used": 4146530000.0,
      "adjustments": [],
      "net_adjustment_total": 0.0,
      "filing_date": "2022-09-30",
      "form": "10-Q",
      "ai_analysis": {
        "health": "Good",
        "comment": "調整項目はありません。GAAP EPSがそのまま実質EPSと見なせます。",
        "sources": []
      }
    },
    {
      "gaap_eps": -0.04363662820548384,
      "adjusted_eps": -0.04363662820548384,
      "gaap_net_income": -179329000.0,
      "adjusted_net_income": -179329000.0,
      "diluted_shares_used": 4109598000.0,
      "adjustments": [],
      "net_adjustment_total": 0.0,
      "filing_date": "2022-06-30",
      "form": "10-Q",
      "ai_analysis": {
        "health": "Good",
        "comment": "調整項目はありません。GAAP EPSがそのまま実質EPSと見なせます。",
        "sources": []
      }
    },
    {
      "gaap_eps": -0.024892857511170957,
      "adjusted_eps": 0.004072610367690137,
      "gaap_net_income": -101379000.0,
      "adjusted_net_income": 16586170.0,
      "diluted_shares_used": 4072614000.0,
      "adjustments": [
        {
          "item_name": "株式報酬費用",
          "amount": 149323000,
          "unit": "USD",
          "direction": "add_back",
          "pre_tax": true,
          "reason": "非現金費用（ConfigでON/OFF可）",
          "extracted_from": "us-gaap:ShareBasedCompensation",
          "category": "株式報酬 (SBC)",
          "net_amount": 117965170.0,
          "tax_rate_applied": 0.21
        }
      ],
      "net_adjustment_total": 117965170.0,
      "filing_date": "2022-03-31",
      "form": "10-Q",
      "ai_analysis": {
        "health": "Caution",
        "comment": "調整項目は株式報酬費用の加算のみで、非現金費用として一般的な調整です。ただし、GAAP EPSが赤字(-0.025)から調整後EPSが黒字(0.004)へ転換しており、SBCによる実質的な株主希薄化コストを考慮すると過度に楽観的な印象を与える可能性があります。単一項目で透明性は高いものの、継続的なSBC依存に注意が必要です。",
        "sources": [
          {
            "item": "株式報酬費用",
            "snippet": "非現金費用（ConfigでON/OFF可）"
          }
        ]
      }
    },
    {
      "gaap_eps": -0.02599706270887474,
      "adjusted_eps": -0.02599706270887474,
      "gaap_net_income": -102137000.0,
      "adjusted_net_income": -102137000.0,
      "diluted_shares_used": 3928790000.0,
      "adjustments": [],
      "net_adjustment_total": 0.0,
      "filing_date": "2021-09-30",
      "form": "10-Q",
      "ai_analysis": {
        "health": "Good",
        "comment": "調整項目はありません。GAAP EPSがそのまま実質EPSと見なせます。",
        "sources": []
      }
    },
    {
      "gaap_eps": -0.03657224773910776,
      "adjusted_eps": -0.03657224773910776,
      "gaap_net_income": -138580000.0,
      "adjusted_net_income": -138580000.0,
      "diluted_shares_used": 3789212000.0,
      "adjustments": [],
      "net_adjustment_total": 0.0,
      "filing_date": "2021-06-30",
      "form": "10-Q",
      "ai_analysis": {
        "health": "Good",
        "comment": "調整項目はありません。GAAP EPSがそのまま実質EPSと見なせます。",
        "sources": []
      }
    },
    {
      "gaap_eps": -0.033899859320278634,
      "adjusted_eps": 0.008119419072919538,
      "gaap_net_income": -123474000.0,
      "adjusted_net_income": 29573490.0,
      "diluted_shares_used": 3642316000.0,
      "adjustments": [
        {
          "item_name": "株式報酬費用",
          "amount": 193731000,
          "unit": "USD",
          "direction": "add_back",
          "pre_tax": true,
          "reason": "非現金費用（ConfigでON/OFF可）",
          "extracted_from": "us-gaap:ShareBasedCompensation",
          "category": "株式報酬 (SBC)",
          "net_amount": 153047490.0,
          "tax_rate_applied": 0.21
        }
      ],
      "net_adjustment_total": 153047490.0,
      "filing_date": "2021-03-31",
      "form": "10-Q",
      "ai_analysis": {
        "health": "Caution",
        "comment": "GAAP EPSが赤字(-0.034)である一方、株式報酬費用(約1.94億ドル)の加算によりAdjusted EPSが黒字化しています。SBCは非現金費用としてよく調整されますが、PLTRのような企業では金額が大きく、調整後利益を過度に楽観視するリスクがあります。持続的な収益性に注意が必要です。",
        "sources": [
          {
            "item": "株式報酬費用",
            "snippet": "amount: 193731000, direction: add_back, reason: 非現金費用（ConfigでON/OFF可）, category: 株式報酬 (SBC)"
          }
        ]
      }
    },
    {
      "gaap_eps": -0.4712064091524194,
      "adjusted_eps": -0.46754198151031195,
      "gaap_net_income": -853319000.0,
      "adjusted_net_income": -846683000.0,
      "diluted_shares_used": 1810924010.0,
      "adjustments": [
        {
          "item_name": "株式報酬費用",
          "amount": 8400000,
          "unit": "USD",
          "direction": "add_back",
          "pre_tax": true,
          "reason": "非現金費用（ConfigでON/OFF可）",
          "extracted_from": "us-gaap:ShareBasedCompensation",
          "category": "株式報酬 (SBC)",
          "net_amount": 6636000.0,
          "tax_rate_applied": 0.21
        }
      ],
      "net_adjustment_total": 6636000.0,
      "filing_date": "2020-09-30",
      "form": "10-Q",
      "ai_analysis": {
        "health": "Good",
        "comment": "唯一の調整項目は株式報酬費用（SBC）のadd_backです。非現金費用として標準的な調整であり、GAAP EPSとAdjusted EPSの差が約0.0037と非常に小さいため、調整の影響は限定的で財務健全性は良好です。",
        "sources": [
          {
            "item": "株式報酬費用",
            "snippet": "非現金費用（ConfigでON/OFF可）"
          }
        ]
      }
    },
    {
      "gaap_eps": -0.17240571964618234,
      "adjusted_eps": -0.17240571964618234,
      "gaap_net_income": -110455000.0,
      "adjusted_net_income": -110455000.0,
      "diluted_shares_used": 640669000.0,
      "adjustments": [],
      "net_adjustment_total": 0.0,
      "filing_date": "2020-06-30",
      "form": "10-Q",
      "ai_analysis": {
        "health": "Good",
        "comment": "調整項目はありません。GAAP EPSがそのまま実質EPSと見なせます。",
        "sources": []
      }
    },
    {
      "gaap_eps": -0.09131456702385579,
      "adjusted_eps": -0.01939802780455715,
      "gaap_net_income": -54274000.0,
      "adjusted_net_income": -11529470.0,
      "diluted_shares_used": 594363000.0,
      "adjustments": [
        {
          "item_name": "株式報酬費用",
          "amount": 54107000,
          "unit": "USD",
          "direction": "add_back",
          "pre_tax": true,
          "reason": "非現金費用（ConfigでON/OFF可）",
          "extracted_from": "us-gaap:ShareBasedCompensation",
          "category": "株式報酬 (SBC)",
          "net_amount": 42744530.0,
          "tax_rate_applied": 0.21
        }
      ],
      "net_adjustment_total": 42744530.0,
      "filing_date": "2020-03-31",
      "form": "10-Q",
      "ai_analysis": {
        "health": "Caution",
        "comment": "株式報酬費用の加算戻しによりGAAP EPSからAdjusted EPSへの大幅な改善が見られますが、SBCは株主希薄化を伴う実質的なコストであるため調整の健全性は注意が必要です。2020年3月期という上場前後の時期で金額も大きい点が懸念されます。",
        "sources": [
          {
            "item": "株式報酬費用",
            "snippet": "非現金費用（ConfigでON/OFF可）"
          }
        ]
      }
    },
    {
      "gaap_eps": -0.2410943486584837,
      "adjusted_eps": -0.2410943486584837,
      "gaap_net_income": -139860000.0,
      "adjusted_net_income": -139860000.0,
      "diluted_shares_used": 580104846.0,
      "adjustments": [],
      "net_adjustment_total": 0.0,
      "filing_date": "2019-09-30",
      "form": "10-Q",
      "ai_analysis": {
        "health": "Good",
        "comment": "調整項目はありません。GAAP EPSがそのまま実質EPSと見なせます。",
        "sources": []
      }
    }
  ]
}